{
    "cardArray": [
        {
            "name": "jupiter",
            "image": "images/jupiter.jpg"
        },
        {
            "name": "jupiter",
            "image": "images/jupiter.jpg"
        },
        {
            "name": "mars",
            "image": "images/mars.jpg"
        },
        {
            "name": "mars",
            "image": "images/mars.jpg"
        },
        {
            "name": "neptun",
            "image": "images/neptun.jpg"
        },
        {
            "name": "neptun",
            "image": "images/neptun.jpg"
        },
        {
            "name": "earth",
            "image": "images/earth.jpg"
        },
        {
            "name": "earth",
            "image": "images/earth.jpg"
        }
    ]
}